{
  "accentColor": "{{appsmith.theme.colors.primaryColor}}",
  "animateLoading": true,
  "borderColor": "#E0DEDE",
  "borderRadius": "{{appsmith.theme.borderRadius.appBorderRadius}}",
  "borderWidth": "1",
  "bottomRow": 66,
  "boxShadow": "{{appsmith.theme.boxShadow.appBoxShadow}}",
  "cachedTableData": {},
  "canFreezeColumn": true,
  "childStylesheet": {
    "button": {
      "borderRadius": "{{appsmith.theme.borderRadius.appBorderRadius}}",
      "boxShadow": "none",
      "buttonColor": "{{appsmith.theme.colors.primaryColor}}"
    },
    "editActions": {
      "discardBorderRadius": "{{appsmith.theme.borderRadius.appBorderRadius}}",
      "discardButtonColor": "{{appsmith.theme.colors.primaryColor}}",
      "saveBorderRadius": "{{appsmith.theme.borderRadius.appBorderRadius}}",
      "saveButtonColor": "{{appsmith.theme.colors.primaryColor}}"
    },
    "iconButton": {
      "borderRadius": "{{appsmith.theme.borderRadius.appBorderRadius}}",
      "boxShadow": "none",
      "buttonColor": "{{appsmith.theme.colors.primaryColor}}"
    },
    "menuButton": {
      "borderRadius": "{{appsmith.theme.borderRadius.appBorderRadius}}",
      "boxShadow": "none",
      "menuColor": "{{appsmith.theme.colors.primaryColor}}"
    }
  },
  "columnOrder": [
    "id_orden",
    "producto",
    "cantidad",
    "total_isk",
    "estacion_destino",
    "estado_logistico",
    "fecha_orden",
    "customColumn1"
  ],
  "columnUpdatedAt": 1775408613438,
  "columnWidthMap": {
    "cantidad": 125,
    "estacion_destino": 160,
    "estado_logistico": 162,
    "fecha_orden": 143,
    "id_orden": 113,
    "total_isk": 126
  },
  "customIsLoading": false,
  "customIsLoadingValue": "",
  "defaultPageSize": 0,
  "defaultSelectedRowIndex": 0,
  "defaultSelectedRowIndices": [
    0
  ],
  "delimiter": ",",
  "dynamicBindingPathList": [
    {
      "key": "accentColor"
    },
    {
      "key": "borderRadius"
    },
    {
      "key": "boxShadow"
    },
    {
      "key": "tableData"
    },
    {
      "key": "primaryColumns.id_orden.computedValue"
    },
    {
      "key": "primaryColumns.producto.computedValue"
    },
    {
      "key": "primaryColumns.cantidad.computedValue"
    },
    {
      "key": "primaryColumns.total_isk.computedValue"
    },
    {
      "key": "primaryColumns.estacion_destino.computedValue"
    },
    {
      "key": "primaryColumns.estado_logistico.computedValue"
    },
    {
      "key": "primaryColumns.fecha_orden.computedValue"
    },
    {
      "key": "primaryColumns.customColumn1.borderRadius"
    },
    {
      "key": "primaryColumns.customColumn1.boxShadow"
    },
    {
      "key": "primaryColumns.customColumn1.isDisabled"
    },
    {
      "key": "primaryColumns.producto.label"
    },
    {
      "key": "primaryColumns.id_orden.label"
    },
    {
      "key": "primaryColumns.cantidad.label"
    },
    {
      "key": "primaryColumns.total_isk.label"
    },
    {
      "key": "primaryColumns.estacion_destino.label"
    },
    {
      "key": "primaryColumns.estado_logistico.label"
    },
    {
      "key": "primaryColumns.fecha_orden.label"
    },
    {
      "key": "primaryColumns.customColumn1.label"
    },
    {
      "key": "primaryColumns.customColumn1.alias"
    },
    {
      "key": "primaryColumns.customColumn1.buttonLabel"
    }
  ],
  "dynamicPropertyPathList": [
    {
      "key": "tableData"
    },
    {
      "key": "primaryColumns.customColumn1.isDisabled"
    },
    {
      "key": "primaryColumns.customColumn1.onClick"
    }
  ],
  "dynamicTriggerPathList": [
    {
      "key": "primaryColumns.customColumn1.onClick"
    }
  ],
  "enableClientSideSearch": true,
  "endOfData": false,
  "flexVerticalAlignment": "start",
  "horizontalAlignment": "LEFT",
  "inlineEditingSaveOption": "ROW_LEVEL",
  "isLoading": false,
  "isSortable": true,
  "isVisible": true,
  "isVisibleDownload": true,
  "isVisibleFilters": false,
  "isVisiblePagination": true,
  "isVisibleSearch": true,
  "key": "8t434do9ue",
  "label": "Data",
  "leftColumn": 2,
  "minWidth": 450,
  "mobileBottomRow": 44,
  "mobileLeftColumn": 0,
  "mobileRightColumn": 26,
  "mobileTopRow": 16,
  "needsErrorInfo": false,
  "parentColumnSpace": 20.25,
  "parentId": "0",
  "parentRowSpace": 10,
  "primaryColumns": {
    "cantidad": {
      "alias": "cantidad",
      "allowCellWrapping": false,
      "allowSameOptionsInNewRow": true,
      "columnType": "number",
      "computedValue": "{{(() => { const tableData = Table1.processedTableData || []; return tableData.length > 0 ? tableData.map((currentRow, currentIndex) => (currentRow[\"cantidad\"])) : cantidad })()}}",
      "currencyCode": "USD",
      "decimals": 0,
      "enableFilter": true,
      "enableSort": true,
      "horizontalAlignment": "LEFT",
      "id": "cantidad",
      "index": 2,
      "isCellEditable": false,
      "isCellVisible": true,
      "isDerived": false,
      "isDisabled": false,
      "isDiscardVisible": true,
      "isEditable": false,
      "isSaveVisible": true,
      "isVisible": true,
      "label": "{{ Motor_i18n.t('Dashboard_Cliente', 'col_cantidad') }}",
      "notation": "standard",
      "originalId": "cantidad",
      "sticky": "",
      "textSize": "0.875rem",
      "thousandSeparator": true,
      "validation": {},
      "verticalAlignment": "CENTER",
      "width": 150
    },
    "customColumn1": {
      "alias": "{{ Motor_i18n.t('Dashboard_Cliente', 'col_accion') }}",
      "allowCellWrapping": false,
      "allowSameOptionsInNewRow": true,
      "borderRadius": "{{Table1.processedTableData.map((currentRow, currentIndex) => ( (appsmith.theme.borderRadius.appBorderRadius)))}}",
      "boxShadow": "{{Table1.processedTableData.map((currentRow, currentIndex) => ( \"none\"))}}",
      "buttonColor": "#ef4444",
      "buttonLabel": "{{(() => { const tableData = Table1.processedTableData || []; return tableData.length > 0 ? tableData.map((currentRow, currentIndex) => ( Motor_i18n.t('Dashboard_Cliente', 'estado_pendiente') )) :  Motor_i18n.t('Dashboard_Cliente', 'estado_pendiente')  })()}}",
      "buttonStyle": "rgb(3, 179, 101)",
      "columnType": "button",
      "computedValue": "",
      "currencyCode": "USD",
      "customAlias": "",
      "decimals": 0,
      "enableFilter": true,
      "enableSort": true,
      "horizontalAlignment": "LEFT",
      "id": "customColumn1",
      "index": 7,
      "isCellEditable": false,
      "isCellVisible": true,
      "isDerived": true,
      "isDisabled": "{{(() => { const tableData = Table1.processedTableData || []; return tableData.length > 0 ? tableData.map((currentRow, currentIndex) => ( currentRow.estado_logistico !== 'Pendiente de Entrega' )) :  currentRow.estado_logistico !== 'Pendiente de Entrega'  })()}}",
      "isDiscardVisible": true,
      "isEditable": false,
      "isSaveVisible": true,
      "isVisible": true,
      "label": "{{ Motor_i18n.t('Dashboard_Cliente', 'col_accion') }}",
      "labelColor": "#FFFFFF",
      "notation": "standard",
      "onClick": "{{\n  Devolver_Stock_Cliente.run()\n  .then(() => Cancelar_Orden.run()) // Asegúrate de que este sea el nombre de tu consulta que cambia el estado a 'Cancelado'\n  .then(() => {\n    showAlert('Orden cancelada. Los ítems han regresado al mercado.', 'success');\n    Leer_Mis_Ordenes.run(); // Refresca la tabla de órdenes del cliente\n  })\n  .catch((error) => {\n    showAlert('Falla en la devolución de stock: ' + error.message, 'error');\n  })\n}}",
      "originalId": "customColumn1",
      "sticky": "",
      "textSize": "0.875rem",
      "thousandSeparator": true,
      "validation": {},
      "verticalAlignment": "CENTER",
      "width": 150
    },
    "estacion_destino": {
      "alias": "estacion_destino",
      "allowCellWrapping": false,
      "allowSameOptionsInNewRow": true,
      "columnType": "text",
      "computedValue": "{{(() => { const tableData = Table1.processedTableData || []; return tableData.length > 0 ? tableData.map((currentRow, currentIndex) => (currentRow[\"estacion_destino\"])) : estacion_destino })()}}",
      "currencyCode": "USD",
      "decimals": 0,
      "enableFilter": true,
      "enableSort": true,
      "horizontalAlignment": "LEFT",
      "id": "estacion_destino",
      "index": 4,
      "isCellEditable": false,
      "isCellVisible": true,
      "isDerived": false,
      "isDisabled": false,
      "isDiscardVisible": true,
      "isEditable": false,
      "isSaveVisible": true,
      "isVisible": true,
      "label": "{{ Motor_i18n.t('Dashboard_Cliente', 'col_destino') }}",
      "notation": "standard",
      "originalId": "estacion_destino",
      "sticky": "",
      "textSize": "0.875rem",
      "thousandSeparator": true,
      "validation": {},
      "verticalAlignment": "CENTER",
      "width": 150
    },
    "estado_logistico": {
      "alias": "estado_logistico",
      "allowCellWrapping": false,
      "allowSameOptionsInNewRow": true,
      "columnType": "text",
      "computedValue": "{{(() => { const tableData = Table1.processedTableData || []; return tableData.length > 0 ? tableData.map((currentRow, currentIndex) => ( \n  currentRow[\"estado_logistico\"] === 'Entregado' ? Motor_i18n.t('Dashboard_Cliente', 'estado_entregado') :\n  currentRow[\"estado_logistico\"] === 'Cancelado por Cliente' ? Motor_i18n.t('Dashboard_Cliente', 'estado_cancelado') :\n  currentRow[\"estado_logistico\"] === 'Solicitado' ? Motor_i18n.t('Dashboard_Cliente', 'estado_solicitado') :\n  currentRow[\"estado_logistico\"] === 'En Tránsito' ? Motor_i18n.t('Dashboard_Cliente', 'estado_en_transito') :\n  currentRow[\"estado_logistico\"] \n)) :  \n  currentRow[\"estado_logistico\"] === 'Entregado' ? Motor_i18n.t('Dashboard_Cliente', 'estado_entregado') :\n  currentRow[\"estado_logistico\"] === 'Cancelado por Cliente' ? Motor_i18n.t('Dashboard_Cliente', 'estado_cancelado') :\n  currentRow[\"estado_logistico\"] === 'Solicitado' ? Motor_i18n.t('Dashboard_Cliente', 'estado_solicitado') :\n  currentRow[\"estado_logistico\"] === 'En Tránsito' ? Motor_i18n.t('Dashboard_Cliente', 'estado_en_transito') :\n  currentRow[\"estado_logistico\"] \n })()}}",
      "currencyCode": "USD",
      "decimals": 0,
      "enableFilter": true,
      "enableSort": true,
      "horizontalAlignment": "LEFT",
      "id": "estado_logistico",
      "index": 5,
      "isCellEditable": false,
      "isCellVisible": true,
      "isDerived": false,
      "isDisabled": false,
      "isDiscardVisible": true,
      "isEditable": false,
      "isSaveVisible": true,
      "isVisible": true,
      "label": "{{ Motor_i18n.t('Dashboard_Cliente', 'col_estado') }}",
      "notation": "standard",
      "originalId": "estado_logistico",
      "sticky": "",
      "textSize": "0.875rem",
      "thousandSeparator": true,
      "validation": {},
      "verticalAlignment": "CENTER",
      "width": 150
    },
    "fecha_orden": {
      "alias": "fecha_orden",
      "allowCellWrapping": false,
      "allowSameOptionsInNewRow": true,
      "columnType": "text",
      "computedValue": "{{(() => { const tableData = Table1.processedTableData || []; return tableData.length > 0 ? tableData.map((currentRow, currentIndex) => (currentRow[\"fecha_orden\"])) : fecha_orden })()}}",
      "currencyCode": "USD",
      "decimals": 0,
      "enableFilter": true,
      "enableSort": true,
      "horizontalAlignment": "LEFT",
      "id": "fecha_orden",
      "index": 6,
      "isCellEditable": false,
      "isCellVisible": true,
      "isDerived": false,
      "isDisabled": false,
      "isDiscardVisible": true,
      "isEditable": false,
      "isSaveVisible": true,
      "isVisible": true,
      "label": "{{ Motor_i18n.t('Dashboard_Cliente', 'col_fecha') }}",
      "notation": "standard",
      "originalId": "fecha_orden",
      "sticky": "",
      "textSize": "0.875rem",
      "thousandSeparator": true,
      "validation": {},
      "verticalAlignment": "CENTER",
      "width": 150
    },
    "id_orden": {
      "alias": "id_orden",
      "allowCellWrapping": false,
      "allowSameOptionsInNewRow": true,
      "columnType": "number",
      "computedValue": "{{(() => { const tableData = Table1.processedTableData || []; return tableData.length > 0 ? tableData.map((currentRow, currentIndex) => (currentRow[\"id_orden\"])) : id_orden })()}}",
      "currencyCode": "USD",
      "decimals": 0,
      "enableFilter": true,
      "enableSort": true,
      "horizontalAlignment": "LEFT",
      "id": "id_orden",
      "index": 0,
      "isCellEditable": false,
      "isCellVisible": true,
      "isDerived": false,
      "isDisabled": false,
      "isDiscardVisible": true,
      "isEditable": false,
      "isSaveVisible": true,
      "isVisible": true,
      "label": "{{ Motor_i18n.t('Dashboard_Cliente', 'col_orden') }}",
      "notation": "standard",
      "originalId": "id_orden",
      "sticky": "",
      "textSize": "0.875rem",
      "thousandSeparator": true,
      "validation": {},
      "verticalAlignment": "CENTER",
      "width": 150
    },
    "producto": {
      "alias": "producto",
      "allowCellWrapping": false,
      "allowSameOptionsInNewRow": true,
      "columnType": "text",
      "computedValue": "{{(() => { const tableData = Table1.processedTableData || []; return tableData.length > 0 ? tableData.map((currentRow, currentIndex) => (currentRow[\"producto\"])) : producto })()}}",
      "currencyCode": "USD",
      "decimals": 0,
      "enableFilter": true,
      "enableSort": true,
      "horizontalAlignment": "LEFT",
      "id": "producto",
      "index": 1,
      "isCellEditable": false,
      "isCellVisible": true,
      "isDerived": false,
      "isDisabled": false,
      "isDiscardVisible": true,
      "isEditable": false,
      "isSaveVisible": true,
      "isVisible": true,
      "label": "{{ Motor_i18n.t('Dashboard_Cliente', 'col_producto') }}",
      "notation": "standard",
      "originalId": "producto",
      "sticky": "",
      "textSize": "0.875rem",
      "thousandSeparator": true,
      "validation": {},
      "verticalAlignment": "CENTER",
      "width": 150
    },
    "total_isk": {
      "alias": "total_isk",
      "allowCellWrapping": false,
      "allowSameOptionsInNewRow": true,
      "columnType": "number",
      "computedValue": "{{(() => { const tableData = Table1.processedTableData || []; return tableData.length > 0 ? tableData.map((currentRow, currentIndex) => (currentRow[\"total_isk\"])) : total_isk })()}}",
      "currencyCode": "USD",
      "decimals": 0,
      "enableFilter": true,
      "enableSort": true,
      "horizontalAlignment": "LEFT",
      "id": "total_isk",
      "index": 3,
      "isCellEditable": false,
      "isCellVisible": true,
      "isDerived": false,
      "isDisabled": false,
      "isDiscardVisible": true,
      "isEditable": false,
      "isSaveVisible": true,
      "isVisible": true,
      "label": "{{ Motor_i18n.t('Dashboard_Cliente', 'col_total') }}",
      "notation": "standard",
      "originalId": "total_isk",
      "sticky": "",
      "textSize": "0.875rem",
      "thousandSeparator": true,
      "validation": {},
      "verticalAlignment": "CENTER",
      "width": 150
    }
  },
  "renderMode": "CANVAS",
  "responsiveBehavior": "fill",
  "rightColumn": 61,
  "searchKey": "",
  "tableData": "{{Leer_Mis_Ordenes.data}}",
  "textSize": "0.875rem",
  "topRow": 17,
  "totalRecordsCount": 0,
  "type": "TABLE_WIDGET_V2",
  "version": 2,
  "verticalAlignment": "CENTER",
  "widgetId": "9w5tffpd91",
  "widgetName": "Table1"
}